pycountstutorial/__init__.py
pycountstutorial/core.py
pycountstutorial/data/__init__.py
pycountstutorial/data/einstein.txt
pycountstutorial/data/flatland.txt
pycountstutorial/data/zen.txt
pycountstutorial/datasets.py
pycountstutorial/plotting.py
pycountstutorial-0.3.1.dist-info/LICENSE
pycountstutorial-0.3.1.dist-info/WHEEL
pycountstutorial-0.3.1.dist-info/METADATA
pycountstutorial-0.3.1.dist-info/RECORD
