Metadata-Version: 2.1
Name: pycountstutorial
Version: 0.3.1
Summary: Calculate word counts in a text file.
Home-page: https://github.com/estripling/pycountstutorial
License: BSD 3-Clause
Author: PyCountsTutorial Developers
Requires-Python: >=3.8,<4.0
Classifier: License :: Other/Proprietary License
Classifier: Programming Language :: Python :: 3
Classifier: Programming Language :: Python :: 3.10
Classifier: Programming Language :: Python :: 3.8
Classifier: Programming Language :: Python :: 3.9
Requires-Dist: matplotlib (>=3.5.2,<4.0.0)
